vibe/__init__.py
vibe/cli.py
vibe_framework-0.2.0.dist-info/LICENSE
vibe_framework-0.2.0.dist-info/METADATA
vibe_framework-0.2.0.dist-info/WHEEL
vibe_framework-0.2.0.dist-info/entry_points.txt
vibe_framework-0.2.0.dist-info/RECORD
