Metadata-Version: 2.3
Name: vibe-framework
Version: 0.2.0
Summary: A lightweight Python framework for quick project setup, similar to Django but simpler
License: MIT
Keywords: framework,cli,development,tool
Author: Your Name
Author-email: you@example.com
Requires-Python: >=3.8,<4.0
Classifier: Development Status :: 3 - Alpha
Classifier: Intended Audience :: Developers
Classifier: License :: OSI Approved :: MIT License
Classifier: Programming Language :: Python :: 3
Classifier: Programming Language :: Python :: 3.8
Classifier: Programming Language :: Python :: 3.9
Classifier: Programming Language :: Python :: 3.10
Classifier: Programming Language :: Python :: 3.11
Classifier: Programming Language :: Python :: 3.12
Classifier: Programming Language :: Python :: 3.13
Project-URL: Homepage, https://github.com/yourusername/vibe-framework
Project-URL: Repository, https://github.com/yourusername/vibe-framework
